mariner_rrx/__init__.py
mariner_rrx/build.py
mariner_rrx/get.py
mariner_rrx/install.py
mariner_rrx/install_local.py
mariner_rrx/mar.py
mariner_rrx/uninstall.py
mariner_rrx/upgrade.py
mariner_rrx-1.1.11.data/scripts/mar.py
mariner_rrx-1.1.11.dist-info/LICENSE
mariner_rrx-1.1.11.dist-info/METADATA
mariner_rrx-1.1.11.dist-info/WHEEL
mariner_rrx-1.1.11.dist-info/entry_points.txt
mariner_rrx-1.1.11.dist-info/top_level.txt
mariner_rrx-1.1.11.dist-info/RECORD
